<output xmlns="http://www.openrat.de/template"
   xmlns:xsi="http://www.w3.org/2001/XMLSchema-instance"
   xsi:schemaLocation="http://www.openrat.de/template ../template.xsd"><dummy><form><window name="GLOBAL_PROP"><row><cell><text text="TEMPLATE_NAME"></text></cell><cell><input name="name"></input></cell></row><row><cell colspan="2"><fieldset></fieldset></cell></row><row><cell><text key="file_extension"></text></cell><cell><link action="template" subaction="extension"><text var="extension"></text></link></cell></row><row><cell><text key="file_mimetype"></text></cell><cell><link action="template" subaction="extension"><text var="mime_type"></text></link></cell></row><row><cell colspan="2" class="act"><button type="ok"></button></cell></row></window></form><focus field="name"></focus></dummy></output>